tgwrap/__init__.py
tgwrap/analyze.py
tgwrap/cli.py
tgwrap/command_constructor.py
tgwrap/core/__init__.py
tgwrap/core/config.py
tgwrap/core/constants.py
tgwrap/core/exceptions.py
tgwrap/core/logging.py
tgwrap/core/resource_management.py
tgwrap/core/security.py
tgwrap/deploy.py
tgwrap/inspector-resources-template.yml
tgwrap/inspector.py
tgwrap/main.py
tgwrap/printer.py
tgwrap/services/__init__.py
tgwrap/services/analyzer.py
tgwrap/services/azure.py
tgwrap/services/deployer.py
tgwrap/services/graph_runner.py
tgwrap-1.0.4.dist-info/METADATA
tgwrap-1.0.4.dist-info/WHEEL
tgwrap-1.0.4.dist-info/entry_points.txt
tgwrap-1.0.4.dist-info/licenses/LICENSE
tgwrap-1.0.4.dist-info/RECORD
