Metadata-Version: 2.4
Name: tgwrap
Version: 1.0.4
Summary: A (terragrunt) wrapper around a (tofu|terraform) wrapper around ....
License: MIT
License-File: LICENSE
Keywords: tofu,terraform,terragrunt,terrasafe,python
Author: Gerco Grandia
Author-email: gerco.grandia@4synergy.nl
Requires-Python: >=3.12,<4.0
Classifier: License :: OSI Approved :: MIT License
Classifier: Programming Language :: Python :: 3
Classifier: Programming Language :: Python :: 3.12
Classifier: Programming Language :: Python :: 3.13
Classifier: Programming Language :: Python :: 3.14
Requires-Dist: azure-core (>=1.30.2,<2.0.0)
Requires-Dist: azure-identity (>=1.17.1,<2.0.0)
Requires-Dist: azure-mgmt-authorization (>=4.0.0,<5.0.0)
Requires-Dist: click (>=8.0)
Requires-Dist: inquirer (>=3.1.4,<4.0.0)
Requires-Dist: jinja2 (>=3.1.4,<4.0.0)
Requires-Dist: networkx (>=2.8.8,<3.0.0)
Requires-Dist: packaging (>=23.0,<24.0)
Requires-Dist: pydot (>=1.4.2,<2.0.0)
Requires-Dist: pyyaml (>=6.0)
Requires-Dist: requests (>=2.31.0,<3.0.0)
Requires-Dist: terrasafe (>=0.5.1,<0.6.0)
Project-URL: Documentation, https://codeberg.org/4synergy/tgwrap
Project-URL: Homepage, https://codeberg.org/4synergy/tgwrap
Project-URL: Repository, https://codeberg.org/4synergy/tgwrap
